aas_test_engines/__init__.py
aas_test_engines/__main__.py
aas_test_engines/_generate.py
aas_test_engines/_util.py
aas_test_engines/api.py
aas_test_engines/data_types.py
aas_test_engines/exception.py
aas_test_engines/file.py
aas_test_engines/py.typed
aas_test_engines/result.py
aas_test_engines/data/api/3.0.yml
aas_test_engines/data/file/3.0.yml
aas_test_engines-1.4.0.dist-info/LICENSE
aas_test_engines-1.4.0.dist-info/METADATA
aas_test_engines-1.4.0.dist-info/WHEEL
aas_test_engines-1.4.0.dist-info/entry_points.txt
aas_test_engines-1.4.0.dist-info/top_level.txt
aas_test_engines-1.4.0.dist-info/RECORD
