Metadata-Version: 2.1
Name: aas_test_engines
Version: 1.4.0
Summary: Official test tooling for the Asset Administration Shell
Project-URL: Homepage, https://github.com/admin-shell-io/aas-test-engines
Keywords: asset administration shell,aas,test
Classifier: Programming Language :: Python
Classifier: Programming Language :: Python :: 3
Requires-Python: >=3.6
License-File: LICENSE
Requires-Dist: requests>=2.31
Requires-Dist: pyyaml>=6.0
Requires-Dist: json-schema-tool>=0.4
Requires-Dist: jsonpath-ng>=1.5
Requires-Dist: fences==1.4.0
